LICENSE
vspoetry/__init__.py
vspoetry-0.3.0.dist-info/entry_points.txt
vspoetry-0.3.0.dist-info/LICENSE
vspoetry-0.3.0.dist-info/WHEEL
vspoetry-0.3.0.dist-info/METADATA
vspoetry-0.3.0.dist-info/RECORD
