Metadata-Version: 2.1
Name: vspoetry
Version: 0.3.0
Summary: Automatically save the running poetry virtual environment to your vscode settings.json
Home-page: https://github.com/MattiooFR/vspoetry
License: MIT
Keywords: vscode,poetry
Author: MattiooFR
Author-email: dugue.mathieu@gmail.com
Requires-Python: >=3.5,<4.0
Classifier: License :: OSI Approved :: MIT License
Classifier: Programming Language :: Python :: 3
Classifier: Programming Language :: Python :: 3.5
Classifier: Programming Language :: Python :: 3.6
Classifier: Programming Language :: Python :: 3.7
Classifier: Programming Language :: Python :: 3.8
Requires-Dist: poetry (>=1.0.0,<2.0.0)
Project-URL: Repository, https://github.com/MattiooFR/vspoetry
